tcposcrouter/__init__.py
tcposcrouter/__main__.py
tcposcrouter/frontend.py
tcposcrouter/osc.py
tcposcrouter/router.py
tcposcrouter/websocket.py
tcposcrouter-0.2.0.dist-info/LICENSE
tcposcrouter-0.2.0.dist-info/METADATA
tcposcrouter-0.2.0.dist-info/WHEEL
tcposcrouter-0.2.0.dist-info/entry_points.txt
tcposcrouter-0.2.0.dist-info/top_level.txt
tcposcrouter-0.2.0.dist-info/RECORD
