Metadata-Version: 2.1
Name: tcposcrouter
Version: 0.2.0
Summary: OpenSoundControl message router over TCP
Home-page: https://github.com/bgola/tcposcrouter
Author: Bruno Gola
Author-email: me@bgo.la
License: UNKNOWN
Keywords: osc opensoundcontrol tcp
Platform: UNKNOWN
Classifier: Programming Language :: Python :: 3
Classifier: License :: OSI Approved :: GNU General Public License v3 or later (GPLv3+)
Classifier: Operating System :: OS Independent
Classifier: Framework :: AsyncIO
Requires-Python: >=3.7
Requires-Dist: python-osc
Requires-Dist: sliplib
